Metadata-Version: 2.1
Name: statts
Version: 1.2
Summary: A library for all statistical operations
Home-page: 
Author: Pranendu Bikash Pradhan
Author-email: b219040@iiit-bh.ac.in
License: MIT
Keywords: stats statistics maths
Platform: UNKNOWN
Classifier: Development Status :: 5 - Production/Stable
Classifier: Intended Audience :: Education
Classifier: License :: OSI Approved :: MIT License
Classifier: Programming Language :: Python :: 3
License-File: LICENSE
